pygrace/__info__.py
pygrace/__init__.py
pygrace/axis.py
pygrace/base.py
pygrace/colors.py
pygrace/dataset.py
pygrace/drawing_objects.py
pygrace/fonts.py
pygrace/grace.py
pygrace/graph.py
pygrace/parser.py
pygrace/plot.py
pygrace/project.py
pygrace/extensions/__init__.py
pygrace/extensions/colorbar.py
pygrace/extensions/distribution.py
pygrace/extensions/latex_string.py
pygrace/extensions/multi_grace.py
pygrace/extensions/multi_plot.py
pygrace/extensions/network.py
pygrace/extensions/panel.py
pygrace/extensions/table.py
pygrace/extensions/tree.py
pygrace/interactive/__init__.py
pygrace/interactive/process.py
pygrace/interactive/project.py
pygrace/interactive/session.py
pygrace/styles/__init__.py
pygrace/styles/el.py
pygrace/styles/journals.py
pygrace/styles/metra.py
pygrace/styles/colorbrewer/__init__.py
pygrace/styles/colorbrewer/colorbrewer.dat
pygrace/styles/colorbrewer/colorbrewer.py
pygrace/styles/colorbrewer/colorbrewer_swatches.pdf
pygrace/tests/__init__.py
pygrace/tests/__main__.py
pygrace/tests/test_interactive.py
pygrace/tests/test_templates.py
pygrace-1.7.data/scripts/pygrace_cdf
pygrace-1.7.dist-info/LICENSE
pygrace-1.7.dist-info/METADATA
pygrace-1.7.dist-info/WHEEL
pygrace-1.7.dist-info/top_level.txt
pygrace-1.7.dist-info/RECORD
