Metadata-Version: 2.1
Name: pygrace
Version: 1.7
Summary: Python bindings to xmgrace
Home-page: https://github.com/uqfoundation/pygrace
Download-URL: https://pypi.org/project/pygrace/#files
Author: Mike McKerns
Author-email: mmckerns@uqfoundation.org
Maintainer: Mike McKerns
Maintainer-email: mmckerns@uqfoundation.org
License: BSD-3-Clause
Project-URL: Documentation, http://pygrace.rtfd.io
Project-URL: Source Code, https://github.com/uqfoundation/pygrace
Project-URL: Bug Tracker, https://github.com/uqfoundation/pygrace/issues
Platform: Linux
Platform: Mac
Classifier: Development Status :: 5 - Production/Stable
Classifier: Intended Audience :: Developers
Classifier: Intended Audience :: Science/Research
Classifier: License :: OSI Approved :: BSD License
Classifier: Programming Language :: Python :: 3
Classifier: Programming Language :: Python :: 3.9
Classifier: Programming Language :: Python :: 3.10
Classifier: Programming Language :: Python :: 3.11
Classifier: Programming Language :: Python :: 3.12
Classifier: Programming Language :: Python :: 3.13
Classifier: Programming Language :: Python :: 3.14
Classifier: Programming Language :: Python :: Implementation :: CPython
Classifier: Programming Language :: Python :: Implementation :: PyPy
Classifier: Topic :: Scientific/Engineering
Classifier: Topic :: Software Development
Requires-Python: >=3.9
License-File: LICENSE
Requires-Dist: numpy>=1.0
Requires-Dist: mpmath>=0.19
